setup.py
tictactoe_suraj/__init__.py
tictactoe_suraj/python_code.py
tictactoe_suraj.egg-info/PKG-INFO
tictactoe_suraj.egg-info/SOURCES.txt
tictactoe_suraj.egg-info/dependency_links.txt
tictactoe_suraj.egg-info/not-zip-safe
tictactoe_suraj.egg-info/top_level.txt